yk_face_api_models/__init__.py
yk_face_api_models/create_qrcode_response.py
yk_face_api_models/gallery_response.py
yk_face_api_models/identify_image_request.py
yk_face_api_models/identify_request.py
yk_face_api_models/process_multiple_request.py
yk_face_api_models/process_request.py
yk_face_api_models/process_request_config.py
yk_face_api_models/processing_enum.py
yk_face_api_models/qrcode_data.py
yk_face_api_models/rename_gallery_request.py
yk_face_api_models/template.py
yk_face_api_models/validate_qrcode_request.py
yk_face_api_models/verify_id_request.py
yk_face_api_models/verify_image_request.py
yk_face_api_models/verify_images.py
yk_face_api_models/verify_request.py
yk_face_api_model-3.1.0.dist-info/LICENSE
yk_face_api_model-3.1.0.dist-info/METADATA
yk_face_api_model-3.1.0.dist-info/WHEEL
yk_face_api_model-3.1.0.dist-info/top_level.txt
yk_face_api_model-3.1.0.dist-info/RECORD
