Metadata-Version: 2.1
Name: yk-face-api-model
Version: 3.1.0
Summary: YouFace API data model package.
Home-page: https://www.youverse.id
Author: Youverse
Author-email: tech@youverse.id
License: MIT
Platform: UNKNOWN
Classifier: Programming Language :: Python :: 3
Classifier: License :: OSI Approved :: MIT License
Classifier: Operating System :: OS Independent
Requires-Python: >=3.8
Requires-Dist: pydantic (<3,>=2)
Requires-Dist: yk-utils (<2,>=1.2.0)
